krules_dev/__init__.py
krules_dev/sane_utils/__init__.py
krules_dev/sane_utils/base.py
krules_dev/sane_utils/consts.py
krules_dev/sane_utils/google/__init__.py
krules_dev/sane_utils/google/google.py
krules_dev/sane_utils/pulumi/__init__.py
krules_dev/sane_utils/pulumi/components/__init__.py
krules_dev/sane_utils/pulumi/components/builder.py
krules_dev/sane_utils/pulumi/components/firestore.py
krules_dev/sane_utils/pulumi/components/gke_deployment.py
krules_dev/sane_utils/pulumi/components/gke_secretproviderclass.py
krules_dev/sane_utils/pulumi/components/gke_statefulset.py
krules_dev/sane_utils/pulumi/components/google_artifactregistry.py
krules_dev/sane_utils/pulumi/components/google_cloudrun.py
krules_dev/sane_utils/pulumi/components/google_function.py
krules_dev/sane_utils/pulumi/components/google_pubsub.py
krules_dev/sane_utils/pulumi/components/google_sa.py
krules_dev/sane_utils/pulumi/components/google_storage.py
krules_dev/sane_utils/pulumi/google.py
krules_dev/sane_utils/pulumi/shell.py
krules_dev/sane_utils/stdvars.py
krules_dev_support-0.12.25.dist-info/AUTHORS
krules_dev_support-0.12.25.dist-info/LICENSE
krules_dev_support-0.12.25.dist-info/METADATA
krules_dev_support-0.12.25.dist-info/WHEEL
krules_dev_support-0.12.25.dist-info/RECORD
