Metadata-Version: 2.1
Name: krules-dev-support
Version: 0.12.25
Summary: 
License: Apache-2.0
Author: Airspot
Author-email: info@airspot.tech
Requires-Python: >=3.10,<4.0
Classifier: License :: OSI Approved :: Apache Software License
Classifier: Programming Language :: Python :: 3
Classifier: Programming Language :: Python :: 3.10
Classifier: Programming Language :: Python :: 3.11
Classifier: Programming Language :: Python :: 3.12
Requires-Dist: better-exceptions (>=0.3.3)
Requires-Dist: google-auth (>=2.22.0)
Requires-Dist: google-cloud-secret-manager (>=2.16.4)
Requires-Dist: grpcio (>=1.60.1,<1.61.0)
Requires-Dist: grpcio-status (>=1.60.1,<1.61.0)
Requires-Dist: jinja2 (>=3.0.1)
Requires-Dist: pulumi (>=3.0.0,<4.0.0)
Requires-Dist: pulumi-gcp (>=7.16.0)
Requires-Dist: pulumi-google-native (>=0.31.1)
Requires-Dist: pulumi-kubernetes (>=4.3.0)
Requires-Dist: pulumi_docker (>=4.4.1)
Requires-Dist: python-dotenv (>=0.19.0)
Requires-Dist: pyyaml (>=6.0.1)
Requires-Dist: rich (>=13.5.2)
Requires-Dist: sane-build (>=7.2)
Requires-Dist: sh (>=2.0.4)
Requires-Dist: structlog (>=23.1.0)
